xdb_location/__init__.py
xdb_location/__main__.py
xdb_location/cli.py
xdb_location/data/fix/github-issue-196.fix
xdb_location/data/fix/github-issue-200.fix
xdb_location/data/fix/github-issue-243.fix
xdb_location/data/github-issue-287.bug
xdb_location/data/global_region.csv
xdb_location/data/ip.test.txt
xdb_location/data/ipv4_source.txt
xdb_location/data/ipv6_source.txt
xdb_location/data/segments.tests
xdb_location/data/segments.tests.mixed
xdb_location/utils.py
xdb_location/xdb/__init__.py
xdb_location/xdb/index.py
xdb_location/xdb/ip2region.xdb
xdb_location/xdb/maker.py
xdb_location/xdb/run.py
xdb_location/xdb/segment.py
xdb_location/xdb/util.py
xdb_location/xdb/xdbSearcher.py
xdb_location/xdb_location.py
xdb_location-0.3.0.dist-info/WHEEL
xdb_location-0.3.0.dist-info/entry_points.txt
xdb_location-0.3.0.dist-info/METADATA
xdb_location-0.3.0.dist-info/RECORD
