Metadata-Version: 2.3
Name: xdb-location
Version: 0.3.0
Summary: a geographic information database
Author: hongjian fang
Author-email: hongjian fang <fanghongjian@geetest.com>
License: MIT
Requires-Dist: typer
Requires-Dist: coverage ; extra == 'test'
Requires-Dist: pytest ; extra == 'test'
Requires-Dist: ruff ; extra == 'test'
Requires-Dist: ty ; extra == 'test'
Requires-Dist: ipdb ; extra == 'test'
Maintainer: hongjian fang
Maintainer-email: hongjian fang <fanghongjian@geetest.com>
Requires-Python: >=3.10
Project-URL: bugs, https://github.com/gunhe/xdb_location/issues
Project-URL: changelog, https://github.com/gunhe/xdb_location/blob/master/changelog.md
Project-URL: homepage, https://github.com/gunhe/xdb_location
Provides-Extra: test
